LICENSE
p123client/__init__.py
p123client/client.py
p123client/const.py
p123client/exception.py
p123client/py.typed
p123client/tool/__init__.py
p123client/tool/download.py
p123client/tool/iterdir.py
p123client/tool/upload.py
p123client/type.py
p123client-0.0.9.2.dist-info/LICENSE
p123client-0.0.9.2.dist-info/METADATA
p123client-0.0.9.2.dist-info/WHEEL
p123client-0.0.9.2.dist-info/RECORD
