Metadata-Version: 2.1
Name: p123client
Version: 0.0.9.2
Summary: Python 123 webdisk client.
Home-page: https://github.com/ChenyangGao/p123client
License: MIT
Keywords: 123,webdisk,client
Author: ChenyangGao
Author-email: wosiwujm@gmail.com
Requires-Python: >=3.12,<4.0
Classifier: Development Status :: 4 - Beta
Classifier: Intended Audience :: Developers
Classifier: License :: OSI Approved :: MIT License
Classifier: Operating System :: OS Independent
Classifier: Programming Language :: Python
Classifier: Programming Language :: Python :: 3
Classifier: Programming Language :: Python :: 3.12
Classifier: Programming Language :: Python :: 3.13
Classifier: Programming Language :: Python :: 3 :: Only
Classifier: Topic :: Software Development
Classifier: Topic :: Software Development :: Libraries
Classifier: Topic :: Software Development :: Libraries :: Python Modules
Requires-Dist: httpx
Requires-Dist: httpx_request (>=0.1.8)
Requires-Dist: multidict
Requires-Dist: orjson
Requires-Dist: python-asynctools (>=0.1.3)
Requires-Dist: python-encode_uri (>=0.0.3)
Requires-Dist: python-filewrap (>=0.2.8)
Requires-Dist: python-hashtools (>=0.0.5)
Requires-Dist: python-http_request (>=0.1.0.1)
Requires-Dist: python-httpfile (>=0.0.5)
Requires-Dist: python-iterutils (>=0.2.7)
Requires-Dist: python-property (>=0.0.3)
Requires-Dist: python-undefined (>=0.0.3)
Requires-Dist: qrcode
Requires-Dist: yarl
Project-URL: Repository, https://github.com/ChenyangGao/p123client
